epluscontrol/__init__.py
epluscontrol/control/__init__.py
epluscontrol/control/control_managers/__init__.py
epluscontrol/control/control_managers/base.py
epluscontrol/control/control_managers/standard_control.py
epluscontrol/control/high_level_control/__init__.py
epluscontrol/control/high_level_control/constant_setpoint.py
epluscontrol/control/high_level_control/model_predictive_control.py
epluscontrol/control/high_level_control/night_setback.py
epluscontrol/control/high_level_control/random_setpoint.py
epluscontrol/control/low_level_control/__init__.py
epluscontrol/control/low_level_control/bangbang.py
epluscontrol/control/low_level_control/low_level_base.py
epluscontrol/control/low_level_control/p.py
epluscontrol/control/low_level_control/pi.py
epluscontrol/control/low_level_control/pid.py
epluscontrol/control/parser/__init__.py
epluscontrol/control/parser/grid_parser.py
epluscontrol/control/parser/setpoint_parser.py
epluscontrol/control/parser/weather_parser.py
epluscontrol/energyplus/__init__.py
epluscontrol/energyplus/energyplus_manager.py
epluscontrol/energyplus/utils/__init__.py
epluscontrol/energyplus/utils/actuator_manager.py
epluscontrol/energyplus/utils/eppy_manager.py
epluscontrol/energyplus/utils/file_manager.py
epluscontrol/energyplus/utils/sensor_manager.py
epluscontrol/energyplus/visualization/__init__.py
epluscontrol/energyplus/visualization/plotting.py
epluscontrol/utils/__init__.py
epluscontrol/utils/custom_plot.py
epluscontrol/utils/kpi.py
epluscontrol/utils/mpc_visualizer.py
epluscontrol/utils/statespace.py
epluscontrol-0.1.6.dist-info/licenses/LICENSE.txt
epluscontrol-0.1.6.dist-info/METADATA
epluscontrol-0.1.6.dist-info/WHEEL
epluscontrol-0.1.6.dist-info/top_level.txt
epluscontrol-0.1.6.dist-info/RECORD
